Workbook

Sheet Sheet1
A1: 年份 | B1: 流动比率 | C1: 速动比率 | D1: 资产负债率(%) | E1: 应收账款周转率(次) | F1: 存货周转率(次) | G1: 毛利率(%) | H1: 总资产收益率(%) | I1: 营业收入增长率(%) | J1: 总资产增长率(%) | K1: 利息保障倍数
A2: 2019 | B2: 2.2706287 | C2: 1.7786418 | D2: 29.520097 | E2: 2.17 | F2: 1.5008678 | G2: 46.448335 | H2: -2.7690166 | I2: 107.75329 | J2: 21.238634 | K2: -4.04
A3: 2020 | B3: 1.7659513 | C3: 1.4568278 | D3: 45.188353 | E3: 2.72 | F3: 2.8247007 | G3: 37.367564 | H3: 10.394723 | I3: 110.82407 | J3: 52.977456 | K3: 16.364743
A4: 2021 | B4: 2.3558207 | C4: 1.865933 | D4: 31.406823 | E4: 1.56 | F4: 2.2318849 | G4: 37.705317 | H4: 7.0201546 | I4: -9.0671807 | J4: -15.116964 | K4: 30.220158
A5: 2022 | B5: 1.6399133 | C5: 1.1859914 | D5: 44.350839 | E5: 0.53 | F5: 0.78217926 | G5: 40.140456 | H5: -5.9827223 | I5: -56.620661 | J5: 11.871133 | K5: -16.090151
A6: 2023 | B6: 1.811099 | C6: 1.1541936 | D6: 38.507121 | E6: 0.61 | F6: 0.64501529 | G6: 39.243848 | H6: -3.3551569 | I6: 1.4277037 | J6: -13.397163 | K6: -5.5936758
A7: 2024 | B7: 1.5894887 | C7: 0.98066871 | D7: 41.596028 | E7: 0.68 | F7: 0.61439645 | G7: 26.48819 | H7: -7.9136413 | I7: -20.835122 | J7: -7.6716951 | K7: -12.219796
A8: 2025 | B8: 1.4240517 | C8: 0.91213934 | D8: 48.056435 | E8: 0.94 | F8: 0.7806633 | G8: 32.625041 | H8: -8.0092646 | I8: 29.44323 | J8: -2.8411977 | K8: -8.3541497

Sheet Sheet2
A1: 年份 | B1: 流动比率 | C1: 速动比率 | D1: 资产负债率(%) | E1: 利息保障倍数 | F1: 应收账款周转率(次) | G1: 存货周转率(次) | H1: 毛利率(%) | I1: 总资产收益率(%) | J1: 营业收入增长率(%) | K1: 总资产增长率(%)
A2: 2019 | B2: =(Sheet1!B2-Sheet1!B8)/(Sheet1!B4-Sheet1!B8) -> 0.90856969 | C2: =(Sheet1!C2-Sheet1!C8)/(Sheet1!C4-Sheet1!C8) -> 0.90848005 | D2: =(Sheet1!D8-Sheet1!D2)/(Sheet1!D8-Sheet1!D2) -> 1 | E2: =(Sheet1!K2-Sheet1!K5)/(Sheet1!K4-Sheet1!K5) -> 0.2602045 | F2: =(Sheet1!E2-Sheet1!E5)/(Sheet1!E3-Sheet1!E5) -> 0.74885845 | G2: =(Sheet1!F2-Sheet1!F7)/(Sheet1!F3-Sheet1!F7) -> 0.40106304 | H2: =(Sheet1!G2-Sheet1!G7)/(Sheet1!G2-Sheet1!G7) -> 1 | I2: =(Sheet1!H2-Sheet1!H8)/(Sheet1!H3-Sheet1!H8) -> 0.28473438 | J2: =(Sheet1!I2-Sheet1!I5)/(Sheet1!I3-Sheet1!I5) -> 0.98166092 | K2: =(Sheet1!J2-Sheet1!J4)/(Sheet1!J3-Sheet1!J4) -> 0.53389981
A3: 2020 | B3: =(Sheet1!B3-Sheet1!B8)/(Sheet1!B4-Sheet1!B8) -> 0.36693598 | C3: =(Sheet1!C3-Sheet1!C8)/(Sheet1!C4-Sheet1!C8) -> 0.57107579 | D3: =(Sheet1!D8-Sheet1!D3)/(Sheet1!D8-Sheet1!D2) -> 0.15472749 | E3: =(Sheet1!K3-Sheet1!K5)/(Sheet1!K4-Sheet1!K5) -> 0.70081358 | F3: =(Sheet1!E3-Sheet1!E5)/(Sheet1!E3-Sheet1!E5) -> 1 | G3: =(Sheet1!F3-Sheet1!F7)/(Sheet1!F3-Sheet1!F7) -> 1 | H3: =(Sheet1!G3-Sheet1!G7)/(Sheet1!G2-Sheet1!G7) -> 0.54505485 | I3: =(Sheet1!H3-Sheet1!H8)/(Sheet1!H3-Sheet1!H8) -> 1 | J3: =(Sheet1!I3-Sheet1!I5)/(Sheet1!I3-Sheet1!I5) -> 1 | K3: =(Sheet1!J3-Sheet1!J4)/(Sheet1!J3-Sheet1!J4) -> 1
A4: 2021 | B4: =(Sheet1!B4-Sheet1!B8)/(Sheet1!B4-Sheet1!B8) -> 1 | C4: =(Sheet1!C4-Sheet1!C8)/(Sheet1!C4-Sheet1!C8) -> 1 | D4: =(Sheet1!D8-Sheet1!D4)/(Sheet1!D8-Sheet1!D2) -> 0.89821473 | E4: =(Sheet1!K4-Sheet1!K5)/(Sheet1!K4-Sheet1!K5) -> 1 | F4: =(Sheet1!E4-Sheet1!E5)/(Sheet1!E3-Sheet1!E5) -> 0.47031963 | G4: =(Sheet1!F4-Sheet1!F7)/(Sheet1!F3-Sheet1!F7) -> 0.73179447 | H4: =(Sheet1!G4-Sheet1!G7)/(Sheet1!G2-Sheet1!G7) -> 0.56197623 | I4: =(Sheet1!H4-Sheet1!H8)/(Sheet1!H3-Sheet1!H8) -> 0.81663928 | J4: =(Sheet1!I4-Sheet1!I5)/(Sheet1!I3-Sheet1!I5) -> 0.28399508 | K4: =(Sheet1!J4-Sheet1!J4)/(Sheet1!J3-Sheet1!J4) -> 0
A5: 2022 | B5: =(Sheet1!B5-Sheet1!B8)/(Sheet1!B4-Sheet1!B8) -> 0.23166854 | C5: =(Sheet1!C5-Sheet1!C8)/(Sheet1!C4-Sheet1!C8) -> 0.28711878 | D5: =(Sheet1!D8-Sheet1!D5)/(Sheet1!D8-Sheet1!D2) -> 0.19990977 | E5: =(Sheet1!K5-Sheet1!K5)/(Sheet1!K4-Sheet1!K5) -> 0 | F5: =(Sheet1!E5-Sheet1!E5)/(Sheet1!E3-Sheet1!E5) -> 0 | G5: =(Sheet1!F5-Sheet1!F7)/(Sheet1!F3-Sheet1!F7) -> 0.075909374 | H5: =(Sheet1!G5-Sheet1!G7)/(Sheet1!G2-Sheet1!G7) -> 0.6839763 | I5: =(Sheet1!H5-Sheet1!H8)/(Sheet1!H3-Sheet1!H8) -> 0.1101143 | J5: =(Sheet1!I5-Sheet1!I5)/(Sheet1!I3-Sheet1!I5) -> 0 | K5: =(Sheet1!J5-Sheet1!J4)/(Sheet1!J3-Sheet1!J4) -> 0.39633346
A6: 2023 | B6: =(Sheet1!B6-Sheet1!B8)/(Sheet1!B4-Sheet1!B8) -> 0.4153898 | C6: =(Sheet1!C6-Sheet1!C8)/(Sheet1!C4-Sheet1!C8) -> 0.25378053 | D6: =(Sheet1!D8-Sheet1!D6)/(Sheet1!D8-Sheet1!D2) -> 0.51516723 | E6: =(Sheet1!K6-Sheet1!K5)/(Sheet1!K4-Sheet1!K5) -> 0.22665525 | F6: =(Sheet1!E6-Sheet1!E5)/(Sheet1!E3-Sheet1!E5) -> 0.03652968 | G6: =(Sheet1!F6-Sheet1!F7)/(Sheet1!F3-Sheet1!F7) -> 0.013852774 | H6: =(Sheet1!G6-Sheet1!G7)/(Sheet1!G2-Sheet1!G7) -> 0.63905636 | I6: =(Sheet1!H6-Sheet1!H8)/(Sheet1!H3-Sheet1!H8) -> 0.25288583 | J6: =(Sheet1!I6-Sheet1!I5)/(Sheet1!I3-Sheet1!I5) -> 0.34667179 | K6: =(Sheet1!J6-Sheet1!J4)/(Sheet1!J3-Sheet1!J4) -> 0.025256123
A7: 2024 | B7: =(Sheet1!B7-Sheet1!B8)/(Sheet1!B4-Sheet1!B8) -> 0.17755147 | C7: =(Sheet1!C7-Sheet1!C8)/(Sheet1!C4-Sheet1!C8) -> 0.07184927 | D7: =(Sheet1!D8-Sheet1!D7)/(Sheet1!D8-Sheet1!D2) -> 0.34852657 | E7: =(Sheet1!K7-Sheet1!K5)/(Sheet1!K4-Sheet1!K5) -> 0.083574362 | F7: =(Sheet1!E7-Sheet1!E5)/(Sheet1!E3-Sheet1!E5) -> 0.068493151 | G7: =(Sheet1!F7-Sheet1!F7)/(Sheet1!F3-Sheet1!F7) -> 0 | H7: =(Sheet1!G7-Sheet1!G7)/(Sheet1!G2-Sheet1!G7) -> 0 | I7: =(Sheet1!H7-Sheet1!H8)/(Sheet1!H3-Sheet1!H8) -> 0.0051957913 | J7: =(Sheet1!I7-Sheet1!I5)/(Sheet1!I3-Sheet1!I5) -> 0.21371553 | K7: =(Sheet1!J7-Sheet1!J4)/(Sheet1!J3-Sheet1!J4) -> 0.10933743
A8: 2025 | B8: =(Sheet1!B8-Sheet1!B8)/(Sheet1!B4-Sheet1!B8) -> 0 | C8: =(Sheet1!C8-Sheet1!C8)/(Sheet1!C4-Sheet1!C8) -> 0 | D8: =(Sheet1!D8-Sheet1!D8)/(Sheet1!D8-Sheet1!D2) -> 0 | E8: =(Sheet1!K8-Sheet1!K5)/(Sheet1!K4-Sheet1!K5) -> 0.16704706 | F8: =(Sheet1!E8-Sheet1!E5)/(Sheet1!E3-Sheet1!E5) -> 0.18721461 | G8: =(Sheet1!F8-Sheet1!F7)/(Sheet1!F3-Sheet1!F7) -> 0.075223514 | H8: =(Sheet1!G8-Sheet1!G7)/(Sheet1!G2-Sheet1!G7) -> 0.30745525 | I8: =(Sheet1!H8-Sheet1!H8)/(Sheet1!H3-Sheet1!H8) -> 0 | J8: =(Sheet1!I8-Sheet1!I5)/(Sheet1!I3-Sheet1!I5) -> 0.51398388 | K8: =(Sheet1!J8-Sheet1!J4)/(Sheet1!J3-Sheet1!J4) -> 0.18027566

Sheet Sheet3
A1: 年份 | B1: 销售净利率
A2: 2019 | B2: -6.59
A3: 2020 | B3: 16.27
A4: 2021 | B4: 13.51
A5: 2022 | B5: -25.82
A6: 2023 | B6: -14.07
A7: 2024 | B7: -37.41
A8: 2025 | B8: -27.69
